{
    "version": "3.1.495",
    "architecture": {
        "64bit": {
            "url": "https://github.com/blacktop/ipsw/releases/download/v3.1.495/ipsw_3.1.495_windows_x86_64.zip",
            "bin": [
                "ipsw.exe"
            ],
            "hash": "522882bade33de599f259ef25760a15b815bfbd24d2830e4f6304e3061c2b52c"
        },
        "arm64": {
            "url": "https://github.com/blacktop/ipsw/releases/download/v3.1.495/ipsw_3.1.495_windows_arm64.zip",
            "bin": [
                "ipsw.exe"
            ],
            "hash": "200e7bac4622469de442b95e2ad8a74dcf4f57c3cab866b3f2dea69a0a5efcac"
        }
    },
    "homepage": "https://blacktop.github.io/ipsw",
    "license": "MIT",
    "description": "iOS/macOS Research Swiss Army Knife"
}