{
    "version": "3.1.511",
    "architecture": {
        "64bit": {
            "url": "https://github.com/blacktop/ipsw/releases/download/v3.1.511/ipsw_3.1.511_windows_x86_64.zip",
            "bin": [
                "ipsw.exe"
            ],
            "hash": "906cd5abac4c62d82e7ae2f533401f74dcc664ede940d92252ac049d4a2a19f0"
        },
        "arm64": {
            "url": "https://github.com/blacktop/ipsw/releases/download/v3.1.511/ipsw_3.1.511_windows_arm64.zip",
            "bin": [
                "ipsw.exe"
            ],
            "hash": "fddb8be5dd40d2f73c26e405f4ce1ac56168ac5e1af01a581b877a9e9a9d1254"
        }
    },
    "homepage": "https://blacktop.github.io/ipsw",
    "license": "MIT",
    "description": "iOS/macOS Research Swiss Army Knife"
}