{
    "version": "3.1.618",
    "architecture": {
        "64bit": {
            "url": "https://github.com/blacktop/ipsw/releases/download/v3.1.618/ipsw_3.1.618_windows_x86_64.zip",
            "bin": [
                "ipsw.exe"
            ],
            "hash": "ba3ea793cdb078b92aa1324fa10656c4c394cd26ebe2ee8ca929785d85419d0b"
        },
        "arm64": {
            "url": "https://github.com/blacktop/ipsw/releases/download/v3.1.618/ipsw_3.1.618_windows_arm64.zip",
            "bin": [
                "ipsw.exe"
            ],
            "hash": "b13cd6b0ca0ef0b30cdbecaf87929018811c52e174027bf928c3e6b1613ce3e6"
        }
    },
    "homepage": "https://blacktop.github.io/ipsw",
    "license": "MIT",
    "description": "iOS/macOS Research Swiss Army Knife"
}